[
    {
        "title": "关于公布福州大学关工委2024年“读懂中国”征文获奖名单的决定",
        "date": "2025-01-22",
        "link": "https://youth.fzu.edu.cn/../info/1030/3229.htm"
    },
    {
        "title": "福州大学基层“五好”关工委建设行动方案",
        "date": "2025-01-22",
        "link": "https://youth.fzu.edu.cn/../info/1030/3228.htm"
    },
    {
        "title": "福州大学关工委关于启动2025年“读懂中国”竞赛活动的通知",
        "date": "2024-10-20",
        "link": "https://youth.fzu.edu.cn/../info/1030/3074.htm"
    },
    {
        "title": "关于核对“毛泽东伟大精神品格”征文数量的通知",
        "date": "2024-09-20",
        "link": "https://youth.fzu.edu.cn/../info/1030/3075.htm"
    }
]